alt_utils/__init__.py
alt_utils/data_structures.py
alt_utils-0.0.8.dist-info/METADATA
alt_utils-0.0.8.dist-info/WHEEL
alt_utils-0.0.8.dist-info/licenses/LICENSE
alt_utils-0.0.8.dist-info/RECORD
