Metadata-Version: 2.4
Name: alt-utils
Version: 0.0.8
Summary: Collection of personal utilities
Project-URL: Homepage, https://gitlab.altau.su/alex/alt-utils
Project-URL: Issues, https://gitlab.altau.su/alex/alt-utils/-/issues
Author-email: Alex Tau <altau.pip@gmail.com>
License-File: LICENSE
Classifier: License :: OSI Approved :: Apache Software License
Classifier: Operating System :: OS Independent
Classifier: Programming Language :: Python :: 3
Requires-Python: >=3.8
